moss/__init__.py
moss/geoio_sdk/__init__.py
moss/geoio_sdk/geoio_service.py
moss/geoio_sdk/model/geoio.py
moss/geoio_sdk/model/user.py
moss/geoio_sdk/utils/util.py
moss_geoio_sdk-0.1.12.dist-info/LICENSE
moss_geoio_sdk-0.1.12.dist-info/METADATA
moss_geoio_sdk-0.1.12.dist-info/WHEEL
moss_geoio_sdk-0.1.12.dist-info/RECORD
