Metadata-Version: 2.3
Name: moss_geoio_sdk
Version: 0.1.12
Summary: GeoIO Python SDK
License: MIT
Keywords: moss_geoio
Author: M.O.S.S.Computer Grafik Systeme GmbH
Author-email: develop@moss.de
Maintainer: M.O.S.S.Computer Grafik Systeme GmbH
Maintainer-email: develop@moss.de
Requires-Python: >=3.10,<4.0
Classifier: Development Status :: 5 - Production/Stable
Classifier: Environment :: Console
Classifier: Environment :: Other Environment
Classifier: Intended Audience :: Developers
Classifier: License :: OSI Approved :: MIT License
Classifier: Operating System :: OS Independent
Classifier: Programming Language :: Python :: 3
Classifier: Programming Language :: Python :: 3.10
Classifier: Programming Language :: Python :: 3.11
Classifier: Programming Language :: Python :: 3.12
Classifier: Programming Language :: Python :: 3.13
Classifier: Topic :: Software Development :: Libraries :: Python Modules
Requires-Dist: requests (>=2,<3)
Project-URL: Homepage, https://www.moss.de/
